cli.py
s_lang/__init__.py
s_lang/data_models.py
s_lang/instructions.py
s_lang/parse.py
s_lang/runner.py
s_lang/variables_store.py
s_lang_mta-0.1.7.dist-info/entry_points.txt
s_lang_mta-0.1.7.dist-info/METADATA
s_lang_mta-0.1.7.dist-info/WHEEL
s_lang_mta-0.1.7.dist-info/RECORD
