Metadata-Version: 2.1
Name: s-lang-mta
Version: 0.1.7
Summary: S lang interpreter
Author: Tal Alon
Author-email: talalon369@gmail.com
Requires-Python: >=3.11,<4.0
Classifier: Programming Language :: Python :: 3
Classifier: Programming Language :: Python :: 3.11
Classifier: Programming Language :: Python :: 3.12
Requires-Dist: typer (>=0.9.0,<0.10.0)
